CHANGELOG
MANIFEST.in
Makefile
README
setup.py
stdeb.cfg
Docs/Axon.html
Docs/BaseModules.html
Docs/InternetAdaptionModules.html
Docs/KamaeliaModuleOverview.html
Docs/NetworkProtocolModules.html
Docs/UDPComponents.html
Docs/UtilityModules.html
Docs/cat.gif
Docs/index.html
Docs/Axon/AdaptiveCommsComponent.py.html
Docs/Axon/Axon.py.html
Docs/Axon/AxonExceptions.py.html
Docs/Axon/Component.py.html
Docs/Axon/CoordinatingAssistantTracker.py.html
Docs/Axon/Ipc.py.html
Docs/Axon/Linkage.py.html
Docs/Axon/Microprocess.py.html
Docs/Axon/Postman.py.html
Docs/Axon/Scheduler.py.html
Docs/Axon/__init__.py.html
Docs/Axon/cat.gif
Docs/Axon/debug.py.html
Docs/Axon/debugConfigFile.py.html
Docs/Axon/idGen.py.html
Docs/Axon/util.py.html
Examples/README
Examples/_EXAMPLES_WITH_LEADING_UNDERSCORES_ARE_DISABLED.md
Examples/Backplane/Forwarding.py
Examples/Contrib/Kamaelia.Apps.SA/DataSink.py
Examples/Contrib/Kamaelia.Apps.SA/PeriodicTick.1.py
Examples/Contrib/Kamaelia.Apps.SA/PeriodicTick.2.py
Examples/Contrib/Kamaelia.Apps.SA/PeriodicTick.3.py
Examples/Contrib/Kamaelia.Apps.SA/SingleTick.py
Examples/Contrib/Kamaelia.Apps.SA/TTL.py
Examples/Files/DemoAppend.py
Examples/Files/SimpleReading.py
Examples/GraphVisualisation/BasicGraphVisualisation.py
Examples/GraphVisualisation/README.BasicGraphVisualisation
Examples/GraphVisualisation/README.TopologyVisualiser
Examples/GraphVisualisation/TopologyVisualiser.py
Examples/GraphVisualisation/BasicGraphVisualisation/ParticleDragger.py
Examples/GraphVisualisation/BasicGraphVisualisation/PhysApp1.py
Examples/GraphVisualisation/BasicGraphVisualisation/VisibleParticle.py
Examples/GraphVisualisation/BasicGraphVisualisation/__init__.py
Examples/GraphVisualisation/_3D/HierarchyTopology3D.py
Examples/GraphVisualisation/_3D/PictureHierarchyTopology3D.py
Examples/GraphVisualisation/_3D/README.md
Examples/GraphVisualisation/_CollabViewer/CollabViewer.py
Examples/GraphVisualisation/_CollabViewer/README.md
kamaelia.egg-info/PKG-INFO
kamaelia.egg-info/SOURCES.txt
kamaelia.egg-info/dependency_links.txt
kamaelia.egg-info/top_level.txt