Metadata-Version: 2.1
Name: kamaelia
Version: 1.14.32
Summary: Kamaelia - Multimedia & Server Development Kit
Home-page: http://www.kamaelia.org/
Author: Michael Sparks (sparkslabs)
Author-email: sparks.m@gmail.com
License: Apache Software License
